Workbook

Sheet Année 1
A1: Couts Fixes | G1: Appartenance | H1: 14
G2: Affiliation | H2: 7
B3: Montant Unitaire | C3: Quantité | D3: Montant Total
A4: Locations salles | B4: 160 | C4: 20 | D4: =C4*B4 -> 3200
A5: Creation année 1 | B5: 600 | C5: 1 | D5: =C5*B5 -> 600
A6: Matos | B6: 500 | C6: 1 | D6: =C6*B6 -> 500
A8: Total Année 1 | D8: =SUM(D4:D6) -> 4300
A9: Total Année 2 et suivante | D9: 3500
A12: Recettes | F12: Année 1 | G12: Année Suivante
B13: Tarif unitaire
A14: Affiliés | B14: 130 | D14: =B14*H2 -> 910
A15: Aide congres | B15: 800 | D15: =B15 -> 800
A16: Medailel Autre | D16: 600
A17: Solde | D17: =D8-D14-D15-D16 -> 1990
A19: Solde année suivante | D19: =D9-D14 -> 2590
A21: Tarif par F et S | D21: =D17/H1 -> 142.14286
A22: Capitation | D22: 175
A25: Total | D25: =D21+D22 -> 317.14286

Sheet autres années
B1: Année 1 | C1: Année 2 | D1: Année 3 | E1: Année 4 | F1: Année 5 | G1: Année 6 | H1: Année 7
A2: Nb FF et SS | B2: 14 | C2: 15 | D2: 17 | E2: 19 | F2: 20 | G2: 21 | H2: 22
A3: Nb Affiliés | B3: 7 | C3: 8 | D3: 8 | E3: 9 | F3: 9 | G3: 9 | H3: 10
A4: Total | B4: =B3+B2 -> 21 | C4: =C3+C2 -> 23 | D4: =D3+D2 -> 25 | E4: =E3+E2 -> 28 | F4: =F3+F2 -> 29 | G4: =G3+G2 -> 30 | H4: =H3+H2 -> 32
J5: Capitation | K5: 170
A6: Cout Fixe | B6: ='Année 1'!D8 -> 4300 | C6: ='Année 1'!$D$9 -> 3500 | D6: ='Année 1'!$D$9 -> 3500 | E6: ='Année 1'!$D$9 -> 3500 | F6: ='Année 1'!$D$9 -> 3500 | G6: ='Année 1'!$D$9 -> 3500 | H6: ='Année 1'!$D$9 -> 3500 | J6: Affiliation | K6: ='Année 1'!B14 -> 130
A7: Cout Capitation | B7: =B2*$K$5 -> 2380 | C7: =C2*$K$5 -> 2550 | D7: =D2*$K$5 -> 2890 | E7: =E2*$K$5 -> 3230 | F7: =F2*$K$5 -> 3400 | G7: =G2*$K$5 -> 3570 | H7: =H2*$K$5 -> 3740 | J7: Cotisation A1 | K7: 350
A8: Total | B8: =B6+B7 -> 6680 | C8: =C6+C7 -> 6050 | D8: =D6+D7 -> 6390 | E8: =E6+E7 -> 6730 | F8: =F6+F7 -> 6900 | G8: =G6+G7 -> 7070 | H8: =H6+H7 -> 7240 | J8: Cotisation année +2 | K8: 310
A11: Recettes | B11: =B2*$K7+B3*$K6 -> 5810 | C11: =C2*$K7+C3*$K6 -> 6290 | D11: =D2*$K8+D3*$K6 -> 6310 | E11: =E2*$K8+E3*$K6 -> 7060 | F11: =F2*$K8+F3*$K6 -> 7370 | G11: =G2*$K8+G3*$K6 -> 7680 | H11: =H2*$K8+H3*$K6 -> 8120
A13: Solde | B13: =B11-B8 -> -870 | C13: =C11-C8 -> 240 | D13: =D11-D8 -> -80 | E13: =E11-E8 -> 330 | F13: =F11-F8 -> 470 | G13: =G11-G8 -> 610 | H13: =H11-H8 -> 880
A14: Tresorerie | B14: =800+B13+200 -> 130 | C14: =B14+C13 -> 370 | D14: =C14+D13 -> 290 | E14: =D14+E13 -> 620 | F14: =E14+F13 -> 1090 | G14: =F14+G13 -> 1700 | H14: =G14+H13 -> 2580
B16: Aide region 800
B17: Medaille autre 200
