Workbook

Sheet Ne Pas transmettre  Tranches 
A1: Nom | B1: Prenom | C1: Tranche
A2: AGNOUNA ONANA | B2: Alphonse | C2: 3 | D2: ?
A3: AUER | B3: François Régis | C3: 3
A4: BUR | B4: Patrick | C4: 3
A5: Butterlin | B5: Christophe | C5: 3
A6: Cadona | B6: Alain | C6: 4
A7: CHANSON | B7: Claire
A8: CORNELISE | B8: Claire | C8: 5
A9: Dangoumau | B9: Tristan | C9: 3
A10: Dardenne | B10: Gilles | C10: 4
A11: DEL VECCHIO | B11: Jean Pierre | C11: 3
A12: DILLENSCHNEIDER | B12: Michel | C12: 1
A13: DUBOIS | B13: Jean-Luc | C13: 3
A14: Dupont | B14: Nicolas | C14: 3
A15: FAIVRE | B15: Alain | C15: 4
A16: Guerné | B16: Dominique | C16: 3
A17: Ibba | B17: Jean marc | C17: 3 | D17: ?
A18: Klein | B18: Thomas | C18: 3
A19: LEBOSSÉ | B19: Cédric | C19: 3
A20: luzerne | B20: Christian | C20: 3
A21: POIAREZ | B21: Jean Claude | C21: 3
A22: REYTER | B22: grégory | C22: 3
A23: ROCHE | B23: Dominique
A24: SUSSET | B24: Valérie | C24: 3
A25: TR | B25: Ariane | C25: 3
A26: App 1 | C26: 3
A27: App 2 | C27: 3
A28: App3 | C28: 3
A29: App 4 | C29: 3
A30: App 5 | C30: 3
A33: Tranche 1 | B33: 1 | C33: =COUNTIF(C$2:C$30,B33) -> 1
A34: Tranche 2 | B34: 2 | C34: =COUNTIF(C$2:C$30,B34) -> 0
A35: Tranche 3 | B35: 3 | C35: =COUNTIF(C$2:C$30,B35) -> 22
A36: Tranche 4 | B36: 4 | C36: =COUNTIF(C$2:C$30,B36) -> 3
A37: Tranche 5 | B37: 5 | C37: =COUNTIF(C$2:C$30,B37) -> 1
B39: Total | C39: =SUM(C33:C37) -> 27

Sheet Budget  Previsionnel
A2: Année civile | B2: 2023 | C2: 2024 | D2: 2025 | E2: 2026 | F2: 2027 | G2: 2028 | H2: 2029 | I2: 2030
B3: ='Ne Pas transmettre Tranches '!C33 -> 1
A4: Membres * | B4: 20 | C4: 21 | D4: 23 | E4: 25 | F4: 26 | G4: 27 | H4: 28 | I4: 30
A5: Affiliés | B5: 4 | C5: 6 | D5: 7 | E5: 6 | F5: 6 | G5: 6 | H5: 6 | I5: 6
A6: Effectif total | B6: =SUM(B4:B5) -> 24 | C6: =SUM(C4:C5) -> 27 | D6: =SUM(D4:D5) -> 30 | E6: =SUM(E4:E5) -> 31 | F6: =SUM(F4:F5) -> 32 | G6: =SUM(G4:G5) -> 33 | H6: =SUM(H4:H5) -> 34 | I6: =SUM(I4:I5) -> 36
A8: TENUES | B8: 20 | C8: 20 | D8: 20 | E8: 20 | F8: 20 | G8: 20 | H8: 20 | I8: 20
A10: Achats | B10: 1066 | C10: 0 | D10: 100 | E10: 120 | F10: 140 | G10: 160 | H10: 180 | I10: 200
A11: Locations Mousson (100 X nb ten.) | B11: =B8*100 -> 2000 | C11: =C8*100 -> 2000 | D11: =D8*100 -> 2000 | E11: =E8*100 -> 2000 | F11: =F8*100 -> 2000 | G11: =G8*100 -> 2000 | H11: =H8*100 -> 2000 | I11: =I8*100 -> 2000
A12: Assurances | B12: =140/4 -> 35 | C12: 30 | D12: 140 | E12: 140 | F12: 140 | G12: 140 | H12: 140 | I12: 140
A13: Frais Convent | B13: 500 | C13: 500 | D13: 500 | E13: 500 | F13: 500 | G13: 500 | H13: 500 | I13: 500
A14: Solidarité/frais CAALA | B14: 190 | C14: =190+35+80 -> 305 | D14: 190 | E14: 190 | F14: 190 | G14: 190 | H14: 190 | I14: 190
A15: Affranchissements | B15: 10 | C15: 30 | D15: 35 | E15: 40 | F15: 40 | G15: 40 | H15: 40 | I15: 40
A16: Abonnement numérique | B16: 0 | C16: 90 | D16: 90 | E16: 90 | F16: 90 | G16: 90 | H16: 90 | I16: 90
A17: Frais gestion banque | B17: =5*3 -> 15 | C17: =90 -> 90 | D17: =5*12 -> 60 | E17: =5*12 -> 60 | F17: =5*12 -> 60 | G17: =5*12 -> 60 | H17: =5*12 -> 60 | I17: =5*12 -> 60
A18: Dépenses exceptionnelles | B18: 600 | C18: =40*5+200 -> 400 | D18: 80 | E18: 100 | F18: 120 | G18: 140 | H18: 160 | I18: 180
A19: Banquet d'ordre | B19: =B6*20 -> 480 | C19: =C6*20 -> 540 | D19: =D6*20 -> 600 | E19: =E6*20 -> 620 | F19: =F6*20 -> 640 | G19: =G6*20 -> 660 | H19: =H6*20 -> 680 | I19: =I6*20 -> 720
A20: TOTAL DEPENSES Socrate | B20: =SUM(B10:B19) -> 4896 | C20: =SUM(C10:C19) -> 3985 | D20: =SUM(D10:D19) -> 3795 | E20: =SUM(E10:E19) -> 3860 | F20: =SUM(F10:F19) -> 3920 | G20: =SUM(G10:G19) -> 3980 | H20: =SUM(H10:H19) -> 4040 | I20: =SUM(I10:I19) -> 4120
A21: Capitations GO + CAALA | B21: =B4*(B32+B33) -> 3514 | C21: =C4*(C32+C33) -> 3689.7 | D21: =D4*(D32+D33) -> 4041.1 | E21: =E4*(E32+E33) -> 4392.5 | F21: =F4*(F32+F33) -> 4568.2 | G21: =G4*(G32+G33) -> 4743.9 | H21: =H4*(H32+H33) -> 4919.6 | I21: =I4*(I32+I33) -> 5271
A22: TOTAL DEPENSES BUDGET | B22: =B20+B21 -> 8410 | C22: =C20+C21 -> 7674.7 | D22: =D20+D21 -> 7836.1 | E22: =E20+E21 -> 8252.5 | F22: =F20+F21 -> 8488.2 | G22: =G20+G21 -> 8723.9 | H22: =H20+H21 -> 8959.6 | I22: =I20+I21 -> 9391
A24: Médaille Région | B24: 800
A25: Médailles Loges | B25: =100+100+200+300+300+50+50+200 -> 1300
A26: Cotisations Socrate | B26: =B27-B25-B24 -> 2796 | C26: =C27-C25-C24 -> 3985 | D26: =D27-D25-D24 -> 3795 | E26: =E27-E25-E24 -> 3860 | F26: =F27-F25-F24 -> 3920 | G26: =G27-G25-G24 -> 3980 | H26: =H27-H25-H24 -> 4040 | I26: =I27-I25-I24 -> 4120
A27: TOTAL RECETTES Socrate | B27: =B20 -> 4896 | C27: =C20 -> 3985 | D27: =D20 -> 3795 | E27: =E20 -> 3860 | F27: =F20 -> 3920 | G27: =G20 -> 3980 | H27: =H20 -> 4040 | I27: =I20 -> 4120
A28: Capitations GO + CAALA | B28: =B4*(B32+B33) -> 3514 | C28: =C4*(C32+C33) -> 3689.7 | D28: =D4*(D32+D33) -> 4041.1 | E28: =E4*(E32+E33) -> 4392.5 | F28: =F4*(F32+F33) -> 4568.2 | G28: =G4*(G32+G33) -> 4743.9 | H28: =H4*(H32+H33) -> 4919.6 | I28: =I4*(I32+I33) -> 5271
A29: TOTAL RECETTES BUDGET | B29: =B27+B4*(B32+B33) -> 8410 | C29: =C27+C4*(C32+C33) -> 7674.7 | D29: =D27+D4*(D32+D33) -> 7836.1 | E29: =E27+E4*(E32+E33) -> 8252.5 | F29: =F27+F4*(F32+F33) -> 8488.2 | G29: =G27+G4*(G32+G33) -> 8723.9 | H29: =H27+H4*(H32+H33) -> 8959.6 | I29: =I27+I4*(I32+I33) -> 9391
A31: Cotisation Socrate ** *** | B31: =B26/B6 -> 116.5 | C31: =C26/C6 -> 147.59259 | D31: =D26/D6 -> 126.5 | E31: =E26/E6 -> 124.51613 | F31: =F26/F6 -> 122.5 | G31: =G26/G6 -> 120.60606 | H31: =H26/H6 -> 118.82353 | I31: =I26/I6 -> 114.44444
A32: Capitation GODF | B32: 171.7 | C32: 171.7 | D32: 171.7 | E32: 171.7 | F32: 171.7 | G32: 171.7 | H32: 171.7 | I32: 171.7
A33: Capitation CAALA | B33: 4 | C33: 4 | D33: 4 | E33: 4 | F33: 4 | G33: 4 | H33: 4 | I33: 4
A34: COTISATION MEMBRE | B34: =SUM(B31:B33) -> 292.2 | C34: =SUM(C31:C33) -> 323.29259 | D34: =SUM(D31:D33) -> 302.2 | E34: =SUM(E31:E33) -> 300.21613 | F34: =SUM(F31:F33) -> 298.2 | G34: =SUM(G31:G33) -> 296.30606 | H34: =SUM(H31:H33) -> 294.52353 | I34: =SUM(I31:I33) -> 290.14444
A35: * Capitations des premiers initiés de la Loge comptées en année pleine
A36: ** dont participation 20€ à 1 banquet d'ordre à partir de 2023 (membres et affiliés)
A37: *** montant de la cotisation des affiliés
A39: Pour info, cotisations hors BO : | B39: =B31 -> 116.5 | C39: =C31-20 -> 127.59259 | D39: =D31-20 -> 106.5 | E39: =E31-20 -> 104.51613 | F39: =F31-20 -> 102.5 | G39: =G31-20 -> 100.60606 | H39: =H31-20 -> 98.823529 | I39: =I31-20 -> 94.444444
B40: =B34 -> 292.2 | C40: =C34-20 -> 303.29259 | D40: =D34-20 -> 282.2 | E40: =E34-20 -> 280.21613 | F40: =F34-20 -> 278.2 | G40: =G34-20 -> 276.30606 | H40: =H34-20 -> 274.52353 | I40: =I34-20 -> 270.14444
A41: NOTA : pour chaque initiation compter l'achat des gants et tabliers + droits d'enregistrement GO à facturer aux néophytes.

Sheet Outil de Calcul
A2: Tranche | B2: Nb de FF et SS | C2: % | D2: Montant tranche Affiliés | E2: Montant Total | F2: Cotisation Globale | G2: Total | I2: cotisation-76 | J2: affiliation-76
A3: Tranche 1 | B3: ='Ne Pas transmettre Tranches '!C33 -> 1 | C3: -0.6 | D3: =ROUNDUP(G$15*(1+C3),0) -> 58 | E3: =B3*D3 -> 58 | F3: =Tableau12[[#This Row],[Montant tranche Affiliés]]+B$15 -> 233.7 | G3: =Tableau12[[#This Row],[Nb de FF et SS]]*Tableau12[[#This Row],[Cotisation Globale]] -> 233.7 | I3: =ROUNDUP(Tableau12[[#This Row],[Cotisation Globale]]-76,0) -> 158 | J3: =ROUNDUP(Tableau12[[#This Row],[Montant tranche Affiliés]]-76,0) -> -18
A4: Tranche 2 | B4: ='Ne Pas transmettre Tranches '!C34 -> 0 | C4: -0.3 | D4: =ROUNDUP(G$15*(1+C4),0) -> 100 | E4: =B4*D4 -> 0 | F4: =Tableau12[[#This Row],[Montant tranche Affiliés]]+B$15 -> 275.7 | G4: =Tableau12[[#This Row],[Nb de FF et SS]]*Tableau12[[#This Row],[Cotisation Globale]] -> 0 | I4: =ROUNDUP(Tableau12[[#This Row],[Cotisation Globale]]-76,0) -> 200 | J4: =ROUNDUP(Tableau12[[#This Row],[Montant tranche Affiliés]]-76,0) -> 24
A5: Tranche 3 | B5: ='Ne Pas transmettre Tranches '!C35 -> 22 | C5: 0 | D5: =ROUNDUP(G$15*(1+C5),0) -> 143 | E5: =B5*D5 -> 3146 | F5: =Tableau12[[#This Row],[Montant tranche Affiliés]]+B$15 -> 318.7 | G5: =Tableau12[[#This Row],[Nb de FF et SS]]*Tableau12[[#This Row],[Cotisation Globale]] -> 7011.4 | I5: =ROUNDUP(Tableau12[[#This Row],[Cotisation Globale]]-76,0) -> 243 | J5: =ROUNDUP(Tableau12[[#This Row],[Montant tranche Affiliés]]-76,0) -> 67
A6: Tranche 4 | B6: ='Ne Pas transmettre Tranches '!C36 -> 3 | C6: 0.3 | D6: =ROUNDUP(G$15*(1+C6),0) -> 186 | E6: =B6*D6 -> 558 | F6: =Tableau12[[#This Row],[Montant tranche Affiliés]]+B$15 -> 361.7 | G6: =Tableau12[[#This Row],[Nb de FF et SS]]*Tableau12[[#This Row],[Cotisation Globale]] -> 1085.1 | I6: =ROUNDUP(Tableau12[[#This Row],[Cotisation Globale]]-76,0) -> 286 | J6: =ROUNDUP(Tableau12[[#This Row],[Montant tranche Affiliés]]-76,0) -> 110
A7: Tranche 5 | B7: ='Ne Pas transmettre Tranches '!C37 -> 1 | C7: 0.6 | D7: =ROUNDUP(G$15*(1+C7),0) -> 229 | E7: =B7*D7 -> 229 | F7: =Tableau12[[#This Row],[Montant tranche Affiliés]]+B$15 -> 404.7 | G7: =Tableau12[[#This Row],[Nb de FF et SS]]*Tableau12[[#This Row],[Cotisation Globale]] -> 404.7 | I7: =ROUNDUP(Tableau12[[#This Row],[Cotisation Globale]]-76,0) -> 329 | J7: =ROUNDUP(Tableau12[[#This Row],[Montant tranche Affiliés]]-76,0) -> 153
A8: Total | B8: =SUM(B3:B7) -> 27 | E8: =SUM(E3:E7) -> 3991 | G8: =SUM(G3:G7) -> 8734.9
A10: Nb Affiliés | B10: 6
C14: Budget Total | D14: ='Budget Previsionnel'!C22 -> 7674.7 | F14: Montant median Quote Part Socrate
A15: Capitation + Region | B15: =171.7+4 -> 175.7 | C15: budget hors capitation | D15: =D14-B15*(B8-B10) -> 3985 | F15: X | G15: =D15/(B3*(1+C3)+B4*(1+C4)+B5*(1+C5)+B6*(1+C6)+B7*(1+C7)) -> 142.83154
A16: (2023 = 171,70 + 4 ) | C16: (voir onglet budget)
F17: Montant Moyen | G17: =D15/B8 -> 147.59259

Sheet Tranche
A4: Fraction revenu imposable ( pour une part) | B4: Taux d'imposition | C4: Tranche cotisation
A5: Jusque 10225 € | B5: < -5% | C5: 1
A6: de 10226 à 26070 € | B6: de 5 à 10% | C6: 2
A7: de 26 071 à 74 545 € | B7: de 10 à 15% | C7: 3
A8: de 74546 à 160 336 € | B8: de 15 à 20% | C8: 4
A9: Supérieur à 160 336 € | B9: > 20% | C9: 5
A13: simulateur : | B13: https://simulateur-ir-ifi.impots.gouv.fr/calcul_impot/2023/simplifie/index.htm

Sheet Feuil1
D1: =SUM(D3:D26) -> 7858.78
A2: Dépenses prévisionnelles | B2: Cout unitaire | C2: quantité | D2: Total
A3: Location | B3: 100 | C3: 20 | D3: =B3*C3 -> 2000
A4: nettoyage | B4: 100 | C4: 3 | D4: =B4*C4 -> 300
A5: Achats | D5: =B5*C5 -> 0
A6: Assurances | B6: 30 | C6: 1 | D6: =B6*C6 -> 30
A7: Frais Convent | B7: 500 | C7: 1 | D7: =B7*C7 -> 500
A8: Solidarité/frais CAALA | B8: =190+25+25+80+80 -> 400 | C8: 1 | D8: =B8*C8 -> 400
A9: Affranchissements | B9: 30 | C9: 1 | D9: =B9*C9 -> 30
A10: Abonnement numérique | B10: 100 | C10: 1 | D10: =B10*C10 -> 100
A11: Frais gestion banque | B11: 9.09 | C11: 12 | D11: =B11*C11 -> 109.08
A12: Dépenses exceptionnelles | D12: =B12*C12 -> 0
A13: Banquet d'ordre | B13: 20 | C13: 27 | D13: =B13*C13 -> 540
A14: initiation taxes | B14: 40 | C14: 4 | D14: =B14*C14 -> 160
A24: Capit | B24: 171.7 | D24: =B27*B24 -> 3605.7
A25: Region cotis | B25: 4 | D25: =B27*B25 -> 84
A26: Nb Affiliés | B26: 6
A27: Nb membres | B27: 21
